exploitai/__init__.py
exploitai/attacks/__init__.py
exploitai/attacks/inference/__init__.py
exploitai/attacks/inference/dlg.py
exploitai/attacks/inference/gradient_inversion.py
exploitai/attacks/inference/idlg.py
exploitai/py.typed
exploitai/utils/__init__.py
exploitai-0.4.1.dist-info/WHEEL
exploitai-0.4.1.dist-info/METADATA
exploitai-0.4.1.dist-info/RECORD
