Metadata-Version: 2.3
Name: exploitai
Version: 0.4.1
Summary: AI Model Security Testing Framework for research and education
Keywords: machine-learning,security,privacy,federated-learning,attacks
Author: Tanguy VANSNICK
Author-email: Tanguy VANSNICK <191451@umons.ac.be>
Classifier: Development Status :: 3 - Alpha
Classifier: Intended Audience :: Science/Research
Classifier: License :: OSI Approved :: MIT License
Classifier: Programming Language :: Python :: 3
Classifier: Programming Language :: Python :: 3.11
Classifier: Programming Language :: Python :: 3.12
Classifier: Topic :: Scientific/Engineering :: Artificial Intelligence
Classifier: Topic :: Security
Requires-Dist: torch>=2.0.0
Requires-Dist: torchvision>=0.15.0
Requires-Dist: numpy>=1.24.0
Requires-Dist: matplotlib>=3.6.0
Requires-Dist: tqdm>=4.64.0
Requires-Dist: pytest>=7.0.0 ; extra == 'dev'
Requires-Dist: pytest-cov>=4.0.0 ; extra == 'dev'
Requires-Dist: ruff>=0.1.0 ; extra == 'dev'
Requires-Dist: mypy>=1.5.0 ; extra == 'dev'
Requires-Python: >=3.11
Provides-Extra: dev
